{
  "global": {
    "launch_timeout": 5,
    "focus_retry_delay": 0.02,
    "max_retries": 3,
    "max_log_lines": 1000,
    "tab_switch_delay": 0.02,
    "max_tabs": 20,
    "debug": false
  },
  "window_classes": {},
  "last_focused": {
    "calc": 3281444,
    "sublime_text": 45744574,
    "explorer": 65850
  },
  "app_configs": {
    "bcompare": {
      "window_classes": [
        "TViewForm"
      ],
      "title_required": true,
      "title_includes": [
        "Compare"
      ],
      "title_excludes": [
        "Home"
      ]
    },
    "git-bash": {
      "window_classes": [
        "mintty"
      ],
      "title_required": true,
      "title_includes": [
        "MINGW64"
      ],
      "title_excludes": [],
      "process_name": "mintty.exe"
    },
    "calc": {
      "window_classes": [
        "ApplicationFrameWindow"
      ],
      "title_required": true,
      "title_includes": [
        "Calculator"
      ],
      "title_excludes": [
        "Chrome",
        "MSCTFIME UI",
        "Default IME"
      ],
      "process_name": "Calculator.exe",
      "use_window_name_match": true
    }
  }
}